cigsegy/__init__.py
cigsegy/constinfo.py
cigsegy/createtool.py
cigsegy/deprecated.py
cigsegy/factories.py
cigsegy/interp.py
cigsegy/plot.py
cigsegy/segynp.py
cigsegy/tools.py
cigsegy/transform.py
cigsegy/utils.py
cigsegy/cpp/_CXX_SEGY.cp312-win_amd64.pyd
cigsegy/cpp/segyrw.cpp
cigsegy/cpp/segywrap.cpp
cigsegy-1.2.0.dist-info/LICENSE
cigsegy-1.2.0.dist-info/METADATA
cigsegy-1.2.0.dist-info/WHEEL
cigsegy-1.2.0.dist-info/top_level.txt
cigsegy-1.2.0.dist-info/RECORD
