Metadata-Version: 2.2
Name: cigsegy
Version: 1.2.0
Home-page: https://github.com/JintaoLee-Roger/cigsegy
Author: Jintao Li
License: MIT
Requires-Python: >=3.6
License-File: LICENSE
Requires-Dist: numpy
Requires-Dist: tqdm
Dynamic: author
Dynamic: description
Dynamic: description-content-type
Dynamic: home-page
Dynamic: license
Dynamic: requires-dist
Dynamic: requires-python
